{
  "RawText": "Electronically Recorded in Official Records\r\nRECORDING REQUESTED BY\r\nCounty of Ventura\r\nMONARCH TITLE COMPANY\r\nMichelle Ascencion\r\nAND WHEN RECORDED MAIL DOCUMENT TO:\r\nE/N\r\nVentura County Clerk-Recorder\r\nDOC# 2025000065659\r\nNAME CHARLES D. SHAPIRO and SUZANNE D. SHAPIRO\r\n09/15/2025\r\nSTREET\r\nADDRESS\r\n516 TIMBERWOOD AVENUE\r\nTitles: 1 Pages: 4\r\n08:00 AM\r\nCITY, STATE \u0026\r\nZIP CODE\r\nTHOUSAND OAKS, CA 91360\r\nTotal Fees: $43.00\r\nONTIVD\r\nSPACE ABOVE FOR RECORDER\u0027S USE ONLY\r\nGRANT DEED\r\nTitle of Document\r\nPursuant to Senate Bill 2 - Building Homes and Jobs Act (GC Code Section 27388.1), effective January 1, 2018, a fee of\r\nseventy-five dollars ($75.00) shall be paid at the time of recording of every real estate instrument, paper, or notice required or\r\npermitted by law to be recorded, except those expressly exempted from payment of recording fees, per each single\r\ntransaction per parcel of real property. The fee imposed by this section shall not exceed two hundred twenty-five dollars\r\n($225.00).\r\nExempt from fee per GC 27388.1 (a) (2); recorded concurrently \u0022in connection with\u0022 a transfer subject to the imposition\r\nof documentary transfer tax (DTT).\r\nExempt from fee per GC 27388.1 (a) (2); recorded concurrently \u0022in connection with\u0022 a transfer of real property that is a\r\nresidential dwelling to an owner-occupier.\r\nExempt from fee per GC 27388.1 (a) (1); fee cap of $225.00 reached.\r\nExempt from the fee per GC 27388.1 (a) (1); document transfers real property that is a residential dwelling to an owner-\r\noccupier, or.\r\nTHIS COVER SHEET ADDED TO PROVIDE ADEQUATE SPACE FOR RECORDING INFORMATION\r\n($3.00 Additional Recording Fee Applies)\r\nDOC #2025000065659 Page 2 of 4\r\nRECORDING REQUESTED BY:\r\nMONARCH TITLE COMPANY\r\nEPN\r\nMAIL TAX STATEMENTS AND\r\nWHEN RECORDED MAIL TO:\r\nCHARLES DAVID SHAPIRO\r\nSUZANNE DENISE SHAPIRO\r\n516 TIMBERWOOD AVENUE\r\nTHOUSAND OAKS CA 91360\r\nOrder No.: MT506770\r\nEscrow No.: SHAPIRO\r\nAPN: 551-0-151-585\r\nSPACE ABOVE THIS LINE IS FOR RECORDER\u0027S USE\r\nGRANT DEED\r\nTHE UNDERSIGNED GRANTOR(S) DECLARE(S):\r\nDOCUMENTARY TRANSFER TAX IS $\r\nNo Consideration Due: This conveyance\r\nComputed on full value of property conveyed, or\r\ntransfers an interest into or out of a\r\nComputed on full value less liens and encumbrances remaining at time of sale.\r\nLiving Trust, R\u0026T 11930\r\nCity of THOUSAND OAKS\r\nFor valuable consideration, receipt of which is hereby acknowledged, CHARLES D. SHAPIRO AND\r\nSUZANNE D. SHAPIRO, HUSBAND AND WIFE AS JOINT TENANTS\r\nhereby GRANT(S) to CHARLES DAVID SHAPIRO AND SUZANNE DENISE SHAPIRO, AS CO-\r\nTRUSTEES OF THE SHAPIRO FAMILY TRUST\r\nthe real property situated in the County of\r\nVENTURA\r\n,\r\nState of California, more particularly\r\ndescribed as follows:\r\nSEE ATTACHED EXHIBIT \u0022A\u0022\r\nDated: 9/9/2025\r\nARC CHARLES D. SHAPIRO\r\nSurgane SUZANNE D. SHAPIRO N Shapiro\r\n(SUZANNE D. SHAPIRO)\r\nMAIL TAX STATEMENTS AS DIRECTED ABOVE\r\nDOC #2025000065659 Page 3 of 4\r\nA notary public or other officer completing this certificate verifies only the identity of the individual who signed the\r\ndocument to which this certificate is attached, and not the truthfulness, accuracy, or validity of that document.\r\nSTATE OF CALIFORNIA\r\n)\r\nVentura\r\n) SS.\r\nCOUNTY OF\r\n)\r\nOn\r\n9/9/2025\r\nbefore me,\r\nNicholas Marin\r\n, Notary Public, personally\r\nappeared Charles D. Shapiro and Suzanne D. Shapiro\r\n,\r\nwho proved to me on the basis of satisfactory evidence) to be the person(s) whose name(s) is/are subscribed to the within\r\ninstrument and acknowledged to me that he/she/they executed the same in his/her/their authorized capacity(ies), and that\r\nby his/her/their signature(s) on the instrument the person(s), or the entity upon behalf of which the person(s) acted,\r\nexecuted the instrument.\r\nI certify under PENALTY OF PERJURY under the laws of the State of California that the foregoing paragraph is true and\r\ncorrect.\r\nWITNESS my hand and official seal.\r\nSignature\r\n56\r\n00000000000000000000000000000000000000000000000\r\nNICHOLAS MARIN\r\nCOMM. # 2437574\r\nNOTARY PUBLIC-CALIFORNIA\r\nU\r\nVENTURA COUNTY\r\n1\r\n8\r\nCALIFORNIA\r\nMy Commission Expires MARCH 8, 2027\r\n8\r\n000000000000000000000000000000000000000000000000000\r\nDOC #2025000065659 Page 4 of 4\r\nEXHIBIT \u0022A\u0022\r\nLOT 9 OF TRACT NO. 4305, IN THE CITY OF THOUSAND OAKS, COUNTY OF VENTURA,\r\nSTATE OF CALIFORNIA, AS PER MAP RECORDED IN BOOK 115, PAGE(S) 3 THROUGH 6\r\nOF MAPS IN THE OFFICE OF THE COUNTY RECORDER OF SAID COUNTY.\r\nEXCEPT THEREFROM ALL, GAS OTHER HYDROCARBON SUBSTANCES AND MINERALS\r\nIN AND UNDER SAID LAND, BUT WITHOUT THE RIGHT TO ENTER UPON THE SURFACE\r\nTHEREOF OR WITHIN 500 FEET BENEATH THE SURFACE FOR THE PURPOSE OF\r\nEXPLORING FOR OR EXTRACTING SUCH OIL, GAS OR OTHER HYDROCARBON\r\nSUBSTANCES AND MINERALS.\r\nAPN: 551-0-151-585\r\n\n\n=== Next Document ===\n\nDOC # 2025000065659 09/15/2025 08:00 AM PCOR Page 1 Michelle Ascencion County Clerk-Rec\r\nBOE-502-A (P1) REV. 15 (02-21)\r\nDAN GOODWIN, MAI\r\nPRELIMINARY CHANGE OF OWNERSHIP REPORT\r\nASSESSOR OF VENTURA COUNTY\r\n800 S. Victoria Avenue\r\nTo be completed by the transferee (buyer) prior to a transfer of subject\r\nVentura, CA 93009-1270\r\nproperty, in accordance with section 480.3 of the Revenue and Taxation\r\nassessor.countyofventura.org\r\nCode. A Preliminary Change of Ownership Report must be filed with each\r\n(805) 654-2496\r\nconveyance in the County Recorder\u0027s office for the county where the\r\nproperty is located.\r\nNAME AND MAILING ADDRESS OF BUYER/TRANSFEREE\r\n(Make necessary corrections to the printed name and mailing address)\r\nASSESSOR\u0027S PARCEL NUMBER\r\n551-0-151-585\r\nCHARLES DAVID SHAPIRO\r\nSELLER/TRANSFEROR\r\nSUZANNE DENISE SHAPIRO\r\nCHARLES D. SHAPIRO\r\n516 TIMBERWOOD AVENUE\r\nBUYER\u0027S DAYTIME TELEPHONE NUMBER\r\nTHOUSAND OAKS CA 91360\r\n(\r\n)\r\nN/A\r\nBUYER\u0027S EMAIL ADDRESS\r\nN/A\r\nSTREET ADDRESS OR PHYSICAL LOCATION OF REAL PROPERTY\r\n516 TIMBERWOOD AVENUE THOUSAND OAKS CA 91360\r\nMO\r\nDAY\r\nYEAR\r\nYES\r\nNO\r\nThis property is intended as my principal residence. If YES, please indicate the date of occupancy\r\nor intended occupancy.\r\n06\r\n22\r\n2012\r\nYES\r\nNO\r\nAre you a disabled veteran or a unmarried surviving spouse of a disabled veteran who was\r\ncompensated at 100% by the Department of Veterans Affairs?\r\nMAIL PROPERTY TAX INFORMATION TO (NAME)\r\nCHARLES DAVID SHAPIRO AND SUZANNE DENISE SHAPIRO\r\nMAIL PROPERTY TAX INFORMATION TO (ADDRESS)\r\nCITY\r\nSTATE\r\nZIP CODE\r\n516 TIMBERWOOD AVENUE\r\nTHOUSAND OAKS\r\nCA\r\n91360\r\nPART 1. TRANSFER INFORMATION\r\nPlease complete all statements.\r\nThis section contains possible exclusions from reassessment for certain types of transfers.\r\nYES NO\r\nA. This transfer is solely between spouses (addition or removal of a spouse, death of a spouse, divorce settlement, etc.).\r\nB. This transfer is solely between domestic partners currently registered with the California Secretary of State (addition or removal of\r\na partner, death of a partner, termination settlement, etc.).\r\n* C. This is a transfer:\r\nbetween parent(s) and child(ren)\r\nbetween grandparent(s) and grandchild(ren).\r\nWas this the transferor/grantor\u0027s principal residence?\r\nYES\r\nNO\r\nD. This transfer is the result of a cotenant\u0027s death. Date of death\r\n*\r\nE. This transaction is to replace a principal residence owned by a person 55 years of age or older.\r\nWithin the same county?\r\nYES\r\nNO\r\n* F. This transaction is to replace a principal residence by a person who is severely disabled.\r\nWithin the same county?\r\nYES\r\nNO\r\n*G. This transaction is to replace a principal residence substantially damaged or destroyed by a wildfire or natural disaster for which\r\nthe Governor proclaimed a state of emergency. Within the same county?\r\nYES\r\nNO\r\nH. This transaction is only a correction of the name(s) of the person(s) holding title to the property (e.g., a name change upon marriage).\r\nIf YES, please explain:\r\n1. The recorded document creates, terminates, or reconveys a lender\u0027s interest in the property.\r\nJ. This transaction is recorded only as a requirement for financing purposes or to create, terminate, or reconvey a security interest\r\n(e.g., cosigner). If YES, please explain:\r\nK. The recorded document substitutes a trustee of a trust, mortgage, or other similar document.\r\nL. This is a transfer of property:\r\n1. to/from a revocable trust that may be revoked by the transferor and is for the benefit of\r\n1\r\nthe transferor, and/or\r\n\\\r\nthe transferor\u0027s spouse\r\nregistered domestic partner.\r\n2. to/from an irrevocable trust for the benefit of the\r\ncreator/grantor/trustor and/or\r\ngrantor\u0027s/trustor\u0027s spouse\r\ngrantor\u0027s/trustor\u0027s registered domestic partner.\r\nM. This property is subject to a lease with a remaining lease term of 35 years or more including written options.\r\nN. This is a transfer between parties in which proportional interests of the transferor(s) and transferee(s) in each and every parcel\r\nbeing transferred remain exactly the same after the transfer.\r\nO. This is a transfer subject to subsidized low-income housing requirements with governmentally imposed restrictions, or restrictions\r\nimposed by specified nonprofit corporations.\r\n* P. This transfer is to the first purchaser of a new building containing an active solar energy system.\r\nQ. Other. This transfer is to\r\n* Please refer to the instructions for Part 1.\r\nPlease provide any other Information that will help the Assessor understand the nature of the transfer.\r\nTHIS DOCUMENT IS NOT SUBJECT TO PUBLIC INSPECTION\r\nDOC # 2025000065659 09/15/2025 08:00 AM PCOR Page 2 Michelle Ascencion County Clerk-Rec\r\nDOC #2025000065659 Page 2 of 2\r\nBOE-502-A (P2) REV. 15 (02-21)\r\nPART 2. OTHER TRANSFER INFORMATION\r\nCheck and complete as applicable.\r\nA. Date of transfer, if other than recording date:\r\nB. Type of transfer:\r\nPurchase\r\nForeclosure\r\nGift\r\nTrade or exchange\r\nMerger, stock, or partnership acquisition (Form BOE-100-B)\r\nContract of sale. Date of contract:\r\nInheritance. Date of death:\r\nSale/leaseback\r\nCreation of a lease\r\nAssignment of a lease\r\nTermination of a lease. Date lease began:\r\nOriginal term in years (including written options):\r\nRemaining term in years (including written options):\r\nOther. Please explain:\r\nC. Only a partial interest in the property was transferred.\r\nYES\r\nNO\r\nIf YES, indicate the percentage transferred:\r\n%\r\nPART 3. PURCHASE PRICE AND TERMS OF SALE\r\nCheck and complete as applicable.\r\nA. Total purchase price\r\n$\r\nB. Cash down payment or value of trade or exchange excluding closing costs\r\nAmount $\r\nC. First deed of trust @\r\n% interest for\r\nyears.\r\nMonthly payment $\r\nAmount $\r\nFHA\r\n(\r\nDiscount Points)\r\nCal-Vet\r\nVA ( Discount Points)\r\nFixed rate,\r\nVariable rate\r\nBank/Savings \u0026 Loan/Credit Union\r\nLoan carried by seller\r\nBalloon payment $\r\nDue date:\r\nD. Second deed of trust @\r\n% interest for\r\nyears. Monthly payment $\r\nAmount $\r\nFixed rate\r\nVariable rate\r\nBank/Savings \u0026 Loan/Credit Union\r\nLoan carried by seller\r\nBalloon payment $\r\nDue date:\r\nE. Was an Improvement Bond or other public financing assumed by the buyer?\r\nYES\r\nNO\r\nOutstanding balance $\r\nF. Amount, if any, of real estate commission fees paid by the buyer which are not included in the purchase price\r\n$\r\nG. The property was purchased:\r\nThrough real estate broker. Broker name:\r\nPhone number:\r\nDirect from seller\r\nFrom a family member-Relationship\r\nOther. Please explain:\r\nH. Please explain any special terms, seller concessions, broker/agent/fee waived, financing, and any other information (e.g., buyer assumed the\r\nexisting loan balance) that would assist the Assessor in the valuation of your property.\r\nPART 4. PROPERTY INFORMATION\r\nCheck and complete as applicable.\r\nA. Type of property transferred\r\nSingle-family residence\r\nCo-op/Own-your-own\r\nManufactured home\r\nMultiple-family residence. Number of units:\r\nCondominium\r\nUnimproved lot\r\nOther. Description: (i.e., timber, mineral, water rights, etc.)\r\nTimeshare\r\nCommercial/Industrial\r\nB.\r\nYES\r\nNO Personal/business property, opincentives, provided by seller to buyer are included in the purchase price. Examples of personal\r\nproperty are furniture, farm equipment, machinery, etc. Examples of incentives are club memberships, etc. Attach list if available.\r\nIf YES, enter the value of the personal/business property:\r\n$\r\nIncentives $\r\nC.\r\nYES\r\nNO A manufactured home is included in the purchase price.\r\nIf YES, enter the value attributed to the manufactured home:\r\n$\r\nYES\r\nNO The manufactured/nome is subject to local property tax. If NO, enter decal number:\r\nD.\r\nYES\r\nNO The property produces rental or other income.\r\nIf YES, the income is from:\r\nLease/rent\r\nContract\r\nMineral rights\r\nOther:\r\nE. The condition of the property at the time of sale was:\r\nGood\r\nAverage\r\nFair\r\nPoor\r\nPlease describe:\r\nCERTIFICATION\r\nI certify (or declare) that the foregoing and all information hereon, including any accompanying statements or documents, is true and correct to\r\nthe best of my knowledge and belief.\r\nDATE\r\nNAME SIGNATURE/OF OF BUYER/TRANSFEREE/PERSONAL BUYER/T ANSFEREE OR CORPORATE REPRESENT OFFICER VE/CORPORATE OFFICER Shapro (PLEASE PRINT)\r\n9/9/202\r\n(825)501-9883 TELEPHONE\r\nTITLE\r\nEMAIL ADDRESS\r\nCHARLES DAVID SHAPIRO Suzanne D Shapiro\r\nSuzalashapirea\r\nThe Assessor\u0027s office may contact you for additional information regarding this transaction.\r\nadicom\r\n",
  "FormFields": {
    "Doc1_AND WHEN RECORDED MAIL DOCUMENT TO:": "E/N",
    "Doc1_Exempt from fee per GC 27388.1 (a) (2); recorded concurrently \u0022in connection with\u0022 a transfer subject to the imposition of documentary transfer tax (DTT).": "",
    "Doc1_NAME": "CHARLES D. SHAPIRO and SUZANNE D. SHAPIRO",
    "Doc1_DOC#": "2025000065659",
    "Doc1_CITY, STATE \u0026 ZIP CODE": "THOUSAND OAKS, CA 91360",
    "Doc1_Pages:": "4",
    "Doc1_RECORDING REQUESTED BY": "MONARCH TITLE COMPANY",
    "Doc1_STREET ADDRESS": "516 TIMBERWOOD AVENUE",
    "Doc1_Exempt from the fee per GC 27388.1 (a) (1); document transfers real property that is a residential dwelling to an owner- occupier, or.": "",
    "Doc1_Exempt from fee per GC 27388.1 (a) (2); recorded concurrently \u0022in connection with\u0022 a transfer of real property that is a residential dwelling to an owner-occupier.": "",
    "Doc1_Titles:": "1",
    "Doc1_Exempt from fee per GC 27388.1 (a) (1); fee cap of $225.00 reached.": "",
    "Doc1_Total Fees:": "$43.00",
    "Doc1_Title of Document": "GRANT DEED",
    "Doc1_Electronically Recorded in Official Records County of Ventura": "Michelle Ascencion Ventura County Clerk-Recorder",
    "Doc1_described as follows: SEE ATTACHED EXHIBIT \u0022A\u0022": "",
    "Doc1_For valuable consideration, receipt of which is hereby acknowledged,": "CHARLES D. SHAPIRO AND SUZANNE D. SHAPIRO, HUSBAND AND WIFE AS JOINT TENANTS",
    "Doc1_THE UNDERSIGNED GRANTOR(S) DECLARE(S):": "This conveyance transfers an interest into or out of a Living Trust, R\u0026T 11930",
    "Doc1_APN:": "551-0-151-585",
    "Doc1_Order No.:": "MT506770",
    "Doc1_Escrow No.:": "SHAPIRO",
    "Doc1_Page": "2 of 4 | 3 of 4",
    "Doc1_DOC": "#2025000065659",
    "Doc1_Dated:": "9/9/2025",
    "Doc1_Computed on full value less liens and encumbrances remaining at time of sale.": "",
    "Doc1_Computed on full value of property conveyed, or": "",
    "Doc1_SUZANNE D. SHAPIRO": "Surgane N Shapiro (SUZANNE D. SHAPIRO)",
    "Doc1_RECORDING REQUESTED BY:": "MONARCH TITLE COMPANY EPN CHARLES DAVID SHAPIRO SUZANNE DENISE SHAPIRO 516 TIMBERWOOD AVENUE THOUSAND OAKS CA 91360",
    "Doc1_CHARLES D. SHAPIRO": "ARC",
    "Doc1_City of": "",
    "Doc1_NOTARY PUBLIC-CALIFORNIA U VENTURA COUNTY 1": "NICHOLAS MARIN",
    "Doc1_On": "9/9/2025",
    "Doc1_Signature": "56",
    "Doc1_COUNTY OF": "Ventura",
    "Doc1_COMM.": "# 2437574",
    "Doc1_appeared": "Charles D. Shapiro and Suzanne D. Shapiro",
    "Doc1_before me,": "Nicholas Marin",
    "Doc2_B. This transfer is solely between domestic partners currently registered with the California Secretary of State (addition or removal of a partner, death of a partner, termination settlement, etc.).": "",
    "Doc2_M. This property is subject to a lease with a remaining lease term of 35 years or more including written options.": "",
    "Doc2_N. This is a transfer between parties in which proportional interests of the transferor(s) and transferee(s) in each and every parcel being transferred remain exactly the same after the transfer.": "",
    "Doc2_F. This transaction is to replace a principal residence by a person who is severely disabled.": "",
    "Doc2_K. The recorded document substitutes a trustee of a trust, mortgage, or other similar document.": "",
    "Doc2_1. The recorded document creates, terminates, or reconveys a lender\u0027s interest in the property.": "",
    "Doc2_P. This transfer is to the first purchaser of a new building containing an active solar energy system.": "",
    "Doc2_O. This is a transfer subject to subsidized low-income housing requirements with governmentally imposed restrictions, or restrictions imposed by specified nonprofit corporations.": "",
    "Doc2_STREET ADDRESS OR PHYSICAL LOCATION OF REAL PROPERTY": "516 TIMBERWOOD AVENUE THOUSAND OAKS CA 91360",
    "Doc2_between parent(s) and child(ren)": "",
    "Doc2_YES": "",
    "Doc2_NO": "",
    "Doc2_REV.": "15 (02-21)",
    "Doc2_MAIL PROPERTY TAX INFORMATION TO (NAME)": "CHARLES DAVID SHAPIRO AND SUZANNE DENISE SHAPIRO",
    "Doc2_DAY": "22",
    "Doc2_the transferor\u0027s spouse": "\\",
    "Doc2_YEAR": "2012",
    "Doc2_registered domestic partner.": "",
    "Doc2_SELLER/TRANSFEROR": "CHARLES D. SHAPIRO",
    "Doc2_BUYER\u0027S DAYTIME TELEPHONE NUMBER": "( ) N/A",
    "Doc2_creator/grantor/trustor and/or": "",
    "Doc2_Contract of sale.": "",
    "Doc2_Inheritance.": "",
    "Doc2_Multiple-family residence.": "",
    "Doc2_TELEPHONE": "(825)501-9883",
    "Doc2_Cal-Vet": "",
    "Doc2_Balloon payment $": "",
    "Doc2_Trade or exchange": "",
    "Doc2_Purchase": "",
    "Doc2_Bank/Savings \u0026 Loan/Credit Union": "",
    "Doc2_Other:": "",
    "Doc2_FHA ( Discount Points)": "",
    "Doc2_Mineral rights": "",
    "Doc2_Timeshare": "",
    "Doc2_From a family member-Relationship": "",
    "Doc2_Lease/rent": "",
    "Doc2_Other. Please explain:": "",
    "Doc2_Sale/leaseback": "",
    "Doc2_Fixed rate,": "",
    "Doc2_Merger, stock, or partnership acquisition (Form BOE-100-B)": "",
    "Doc2_Poor": "",
    "Doc2_Foreclosure": "",
    "Doc2_Average": "",
    "Doc2_Manufactured home": "",
    "Doc2_Commercial/Industrial": "",
    "Doc2_Single-family residence": "",
    "Doc2_DATE": "9/9/202",
    "Doc2_Gift": "",
    "Doc2_Fixed rate": "",
    "Doc2_Variable rate": "",
    "Doc2_( Discount Points)": "",
    "Doc2_If YES, indicate the percentage transferred:": "%",
    "Doc2_Good": "",
    "Doc2_Creation of a lease": "",
    "Doc2_EMAIL ADDRESS": "Suzalashapirea",
    "Doc2_Loan carried by seller": "",
    "Doc2_Fair": "",
    "Doc2_Unimproved lot": "",
    "Doc2_Co-op/Own-your-own": "",
    "Doc2_Contract": "",
    "Doc2_Direct from seller": "",
    "Doc2_Condominium": "",
    "Doc2_Assignment of a lease": "",
    "Doc2_Monthly payment": "$",
    "Doc2_Incentives": "$",
    "Doc2_Outstanding balance": "$",
    "Doc2_Amount": "$",
    "Doc2_Termination of a lease. Date lease began:": "",
    "Doc2_Page": "2 of 2",
    "Doc2_Other. Description: (i.e., timber, mineral, water rights, etc.)": "",
    "Doc2_(P2) REV.": "15 (02-21)",
    "Doc2_NAME OF BUYER/TRANSFEREE/PERSONAL REPRESENT VE/CORPORATE OFFICER (PLEASE PRINT)": "CHARLES DAVID SHAPIRO Suzanne D Shapiro The Assessor\u0027s office contact for additional",
    "Doc2_If YES, enter the value attributed to the manufactured home:": "$",
    "Doc2_Page DOC": "2 Michelle Ascencion #2025000065659",
    "Doc2_A. Total purchase price": "$",
    "Doc2_F. Amount, if any, of real estate commission fees paid by the buyer which are not included in the purchase price": "$"
  },
  "TableData": []
}